pooltool/__init__.py
pooltool/ai/__init__.py
pooltool/ai/action.py
pooltool/ai/aim/__init__.py
pooltool/ai/aim/core.py
pooltool/ai/pot/__init__.py
pooltool/ai/pot/core.py
pooltool/ani/__init__.py
pooltool/ani/action.py
pooltool/ani/animate.py
pooltool/ani/camera/__init__.py
pooltool/ani/camera/_camera.py
pooltool/ani/camera/states/7_foot_corner_pocket_zoom.json
pooltool/ani/camera/states/7_foot_offcenter.json
pooltool/ani/camera/states/7_foot_overhead.json
pooltool/ani/camera/states/7_foot_overhead_zoom.json
pooltool/ani/camera/states/7_foot_side_pocket_zoom.json
pooltool/ani/camera/states/__init__.py
pooltool/ani/camera/states/rack.json
pooltool/ani/collision.py
pooltool/ani/constants.py
pooltool/ani/environment.py
pooltool/ani/fonts/HackNerdFontMono-Regular.ttf
pooltool/ani/fonts/LABTSECS.ttf
pooltool/ani/fonts/LABTSECW.ttf
pooltool/ani/fonts/__init__.py
pooltool/ani/globals.py
pooltool/ani/hud.py
pooltool/ani/image/__init__.py
pooltool/ani/image/interface.py
pooltool/ani/image/io.py
pooltool/ani/image/utils.py
pooltool/ani/menu/__init__.py
pooltool/ani/menu/_datatypes.py
pooltool/ani/menu/_factory.py
pooltool/ani/menu/_registry.py
pooltool/ani/menu/menus/__init__.py
pooltool/ani/menu/menus/game_setup.py
pooltool/ani/menu/menus/main_menu.py
pooltool/ani/menu/menus/settings.py
pooltool/ani/modes/__init__.py
pooltool/ani/modes/aim.py
pooltool/ani/modes/ball_in_hand.py
pooltool/ani/modes/calculate.py
pooltool/ani/modes/call_shot.py
pooltool/ani/modes/cam_load.py
pooltool/ani/modes/cam_save.py
pooltool/ani/modes/datatypes.py
pooltool/ani/modes/game_over.py
pooltool/ani/modes/menu.py
pooltool/ani/modes/pick_ball.py
pooltool/ani/modes/purgatory.py
pooltool/ani/modes/shot.py
pooltool/ani/modes/stroke.py
pooltool/ani/modes/view.py
pooltool/ani/mouse.py
pooltool/ani/scene.py
pooltool/ani/tasks.py
pooltool/ani/utils.py
pooltool/config/__init__.py
pooltool/config/paths.py
pooltool/constants.py
pooltool/error.py
pooltool/events/__init__.py
pooltool/events/datatypes.py
pooltool_billiards-0.5.0.dist-info/LICENSE.txt
pooltool_billiards-0.5.0.dist-info/METADATA
pooltool_billiards-0.5.0.dist-info/WHEEL
pooltool_billiards-0.5.0.dist-info/entry_points.txt
pooltool_billiards-0.5.0.dist-info/RECORD
