Metadata-Version: 2.1
Name: pooltool-billiards
Version: 0.5.0
Summary: A sandbox billiards game that emphasizes realistic physics.
Home-page: https://pooltool.readthedocs.io/en/latest/
License: Apache-2.0
Keywords: simulation,physics,pool,billiards,panda3d,snooker,eight-ball
Author: Evan Kiefl
Author-email: kiefl.evan@gmail.com
Maintainer: Evan Kiefl
Maintainer-email: kiefl.evan@gmail.com
Requires-Python: >=3.10,<3.14
Classifier: License :: OSI Approved :: Apache Software License
Classifier: Programming Language :: Python :: 3
Classifier: Programming Language :: Python :: 3.10
Classifier: Programming Language :: Python :: 3.11
Classifier: Programming Language :: Python :: 3.12
Classifier: Programming Language :: Python :: 3.13
Classifier: Topic :: Games/Entertainment :: Simulation
Classifier: Topic :: Scientific/Engineering :: Physics
Classifier: Topic :: Scientific/Engineering :: Visualization
Requires-Dist: Pillow (>=6.2.0)
Requires-Dist: attrs (>=21.3.0)
Requires-Dist: cattrs (>=22.1.0)
Requires-Dist: click (>=8.0.0)
Requires-Dist: h11 (>=0.16.0)
Requires-Dist: h5py (>=3.10)
Requires-Dist: llvmlite (>=0.44.0)
Requires-Dist: msgpack (>=1.0.0)
Requires-Dist: msgpack-numpy (>=0.4.8)
Requires-Dist: numba (>=0.59.0)
Requires-Dist: numpy (>=1.26.0)
Requires-Dist: panda3d (==1.11.0.dev3702) ; sys_platform == "linux"
Requires-Dist: panda3d (==1.11.0.dev3702) ; sys_platform == "win32"
Requires-Dist: panda3d (>=1.10.13,<1.11) ; sys_platform == "darwin"
Requires-Dist: panda3d-gltf (>=1.2.0)
Requires-Dist: panda3d-simplepbr (>=0.12.0)
Requires-Dist: pyyaml (>=5.2)
Requires-Dist: rich (>=14.0.0,<15.0.0)
Requires-Dist: scipy (>=1.12.0)
Project-URL: Documentation, https://pooltool.readthedocs.io/en/latest/
Project-URL: Repository, https://github.com/ekiefl/pooltool
